aws_ci_cd_fargate/__init__.py
aws_ci_cd_fargate/ecs_fargate_with_ci_cd.py
aws_ci_cd_fargate/parameters/__init__.py
aws_ci_cd_fargate/parameters/ecs_parameters.py
aws_ci_cd_fargate/parameters/lb_listener_parameters.py
aws_ci_cd_fargate/parameters/load_balancer_parameters.py
aws_ci_cd_fargate/parameters/pipeline_parameters.py
aws_ci_cd_fargate/source/__init__.py
aws_ci_cd_fargate/source/ecs_main.py
aws_ci_cd_fargate/source/ecs_pipeline.py
aws_ci_cd_fargate/source/lb_listener_config.py
aws_ci_cd_fargate/source/pipeline_commit_to_ecr.py
aws_ci_cd_fargate/source/pipeline_ecr_to_ecs.py
aws_ci_cd_fargate/source/custom/__init__.py
aws_ci_cd_fargate/source/custom/deployment_config.py
aws_ci_cd_fargate/source/custom/deployment_group.py
aws_ci_cd_fargate/source/custom/ecs_service.py
aws_ci_cd_fargate-7.3.0.dist-info/LICENSE
aws_ci_cd_fargate-7.3.0.dist-info/METADATA
aws_ci_cd_fargate-7.3.0.dist-info/WHEEL
aws_ci_cd_fargate-7.3.0.dist-info/top_level.txt
aws_ci_cd_fargate-7.3.0.dist-info/RECORD
