Metadata-Version: 2.1
Name: aws-ci-cd-fargate
Version: 7.3.0
Summary: AWS CDK package that helps deploying a fargate service with ci/cd.
Home-page: https://github.com/idenfy/AwsFargateCdk.git
Author: Deividas Tamkus, Laimonas Sutkus
Author-email: dtamkus@gmail.com (deividas@idenfy.com), laimonas.sutkus@gmail.com (laimonas@idenfy.com)
License: GNU GENERAL PUBLIC LICENSE Version 3
Keywords: AWS CDK Fargate ECS
Platform: UNKNOWN
Classifier: Programming Language :: Python :: 3
Classifier: Operating System :: OS Independent
Requires-Dist: aws-cdk.core (<2.0.0,>=1.60.0)
Requires-Dist: aws-cdk.aws-iam (<2.0.0,>=1.60.0)
Requires-Dist: aws-cdk.custom-resources (<2.0.0,>=1.60.0)
Requires-Dist: aws-cdk.aws-s3 (<2.0.0,>=1.60.0)
Requires-Dist: aws-cdk.aws-certificatemanager (<2.0.0,>=1.60.0)
Requires-Dist: aws-cdk.aws-elasticloadbalancingv2 (<2.0.0,>=1.60.0)
Requires-Dist: aws-cdk.aws-ec2 (<2.0.0,>=1.60.0)
Requires-Dist: aws-cdk.aws-logs (<2.0.0,>=1.60.0)
Requires-Dist: aws-cdk.aws-ecs (<2.0.0,>=1.60.0)
Requires-Dist: aws-cdk.aws-applicationautoscaling (<2.0.0,>=1.60.0)
Requires-Dist: aws-cdk.aws-codedeploy (<2.0.0,>=1.60.0)
Requires-Dist: aws-cdk.aws-codecommit (<2.0.0,>=1.60.0)
Requires-Dist: aws-cdk.aws-codepipeline (<2.0.0,>=1.60.0)
Requires-Dist: aws-cdk.aws-codepipeline-actions (<2.0.0,>=1.60.0)
Requires-Dist: aws-cdk.aws-ecr (<2.0.0,>=1.60.0)
Requires-Dist: aws-cdk.aws-codebuild (<2.0.0,>=1.60.0)
Requires-Dist: aws-empty-bucket (<3.0.0,>=2.0.1)
Requires-Dist: aws-vpc (<3.0.0,>=2.0.0)
Requires-Dist: aws-ecs-service (<2.0.0,>=1.0.7)
Requires-Dist: aws-ecs-cluster (<2.0.0,>=1.0.1)
Requires-Dist: aws-empty-ecr-repository (<2.0.0,>=1.0.2)
